Workbook

Sheet Cover
A1: 🚗 AI Ad Manager
A4: Business Plan & Financial Model
A7: Helping Indian car dealerships run Google & Meta ads — no agency needed.
A10: Industry: AutoTech / Car Dealership — India
A12: Business Model: SaaS Subscription (₹8,999–₹14,999/month per dealership)
A14: Target Market: Indian car dealerships — Tier 1 & Tier 2 cities
A16: Projection Period: FY2025 – FY2029 (5 Years)
A18: 📋 Model Sheets
A21: 1. Cover | 2. Assumptions | 3. Revenue Model | 4. P&L | 5. Cash Flow | 6. Unit Economics | 7. Scenarios
A25: CONFIDENTIAL — For internal use only. All projections are estimates based on market assumptions.

Sheet Assumptions
A1: ASSUMPTIONS & KEY DRIVERS
A2: Parameter | B2: FY2025 | C2: FY2026 | D2: FY2027 | E2: FY2028 | F2: FY2029
A3: MARKET & DEALER ACQUISITION
A4: Total Addressable Dealers (India) | B4: 15000 | C4: 15000 | D4: 15000 | E4: 15000 | F4: 15000
A5: New Dealers Added (per month) | B5: 5 | C5: 12 | D5: 25 | E5: 40 | F5: 55
A6: Monthly Churn Rate | B6: 0.03 | C6: 0.025 | D6: 0.02 | E6: 0.018 | F6: 0.015
A7: PRICING
A8: Single Dealership Plan (₹/month) | B8: 8999 | C8: 8999 | D8: 9499 | E8: 9499 | F8: 9999
A9: Multi-Dealership Plan (₹/month) | B9: 14999 | C9: 14999 | D9: 15999 | E9: 15999 | F9: 16999
A10: % Dealers on Multi Plan | B10: 0.1 | C10: 0.15 | D10: 0.2 | E10: 0.25 | F10: 0.3
A11: Annual Price Escalation | B11: 0 | C11: 0 | D11: 0.056 | E11: 0 | F11: 0.053
A12: COST STRUCTURE
A13: Founding Team Salaries (₹L/month) | B13: 3 | C13: 5 | D13: 8 | E13: 12 | F13: 16
A14: Engineering Headcount (FTEs) | B14: 2 | C14: 4 | D14: 7 | E14: 11 | F14: 15
A15: Avg Engineering Salary (₹L/month) | B15: 1.5 | C15: 1.6 | D15: 1.7 | E15: 1.8 | F15: 1.9
A16: Sales & Marketing Headcount (FTEs) | B16: 2 | C16: 4 | D16: 8 | E16: 14 | F16: 20
A17: Avg Sales Salary (₹L/month) | B17: 0.8 | C17: 0.9 | D17: 1 | E17: 1.1 | F17: 1.2
A18: Infra & API Costs (₹/dealer/month) | B18: 500 | C18: 450 | D18: 400 | E18: 350 | F18: 300
A19: G&A Costs (₹L/month) | B19: 0.5 | C19: 0.8 | D19: 1.2 | E19: 1.8 | F19: 2.5
A20: Sales & Marketing Spend (% Revenue) | B20: 0.3 | C20: 0.25 | D20: 0.22 | E20: 0.2 | F20: 0.18
A21: UNIT ECONOMICS
A22: CAC | B22: =(B16*B17*100000*12)/(B5*12) -> 32000 | C22: =(C16*C17*100000*12)/(C5*12) -> 30000 | D22: =(D16*D17*100000*12)/(D5*12) -> 32000 | E22: =(E16*E17*100000*12)/(E5*12) -> 38500 | F22: =(F16*F17*100000*12)/(F5*12) -> 43636.364
A23: ARPU | B23: =B8*(1-B10)+B9*B10 -> 9599 | C23: =C8*(1-C10)+C9*C10 -> 9899 | D23: =D8*(1-D10)+D9*D10 -> 10799 | E23: =E8*(1-E10)+E9*E10 -> 11124 | F23: =F8*(1-F10)+F9*F10 -> 12099
A24: LTV | B24: =B23/B6 -> 319966.67 | C24: =C23/C6 -> 395960 | D24: =D23/D6 -> 539950 | E24: =E23/E6 -> 618000 | F24: =F23/F6 -> 806600
A25: LTV/CAC | B25: =IF(B22=0,0,B24/B22) -> 9.9989583 | C25: =IF(C22=0,0,C24/C22) -> 13.198667 | D25: =IF(D22=0,0,D24/D22) -> 16.873438 | E25: =IF(E22=0,0,E24/E22) -> 16.051948 | F25: =IF(F22=0,0,F24/F22) -> 18.484583
A26: Payback | B26: =IF(B23=0,0,B22/B23) -> 3.3336806 | C26: =IF(C23=0,0,C23/C22) -> 0.32996667 | D26: =IF(D23=0,0,D23/D22) -> 0.33746875 | E26: =IF(E23=0,0,E23/E22) -> 0.28893506 | F26: =IF(F23=0,0,F23/F22) -> 0.27726875
A28: COLOUR LEGEND
A29: Blue text = Hardcoded input (you can change)
A30: Black text = Formula / calculated value
A31: Green text = Cross-sheet link
A32: Yellow background = Key assumption to review

Sheet Revenue Model
A1: REVENUE MODEL — Monthly Dealer Build-Up & Annual Revenue
B2: FY2025 | C2: FY2026 | D2: FY2027 | E2: FY2028 | F2: FY2029
A3: DEALER COUNT (End of Year)
A4: Beginning Dealers | B4: 0 | C4: =B7 -> 60 | D4: =C7 -> 186 | E4: =D7 -> 441 | F4: =E7 -> 826
A5: New Dealers Added (Annual) | B5: =Assumptions!B5*12 -> 60 | C5: =Assumptions!C5*12 -> 144 | D5: =Assumptions!D5*12 -> 300 | E5: =Assumptions!E5*12 -> 480 | F5: =Assumptions!F5*12 -> 660
A6: Churned Dealers | B6: =-ROUND(B4*Assumptions!B6*12,0) -> 0 | C6: =-ROUND(C4*Assumptions!C6*12,0) -> -18 | D6: =-ROUND(D4*Assumptions!D6*12,0) -> -45 | E6: =-ROUND(E4*Assumptions!E6*12,0) -> -95 | F6: =-ROUND(F4*Assumptions!F6*12,0) -> -149
A7: Ending Dealers | B7: =B4+B5+B6 -> 60 | C7: =C4+C5+C6 -> 186 | D7: =D4+D5+D6 -> 441 | E7: =E4+E5+E6 -> 826 | F7: =F4+F5+F6 -> 1337
A8: Average Active Dealers | B8: =ROUND((B4+B7)/2,0) -> 30 | C8: =ROUND((C4+C7)/2,0) -> 123 | D8: =ROUND((D4+D7)/2,0) -> 314 | E8: =ROUND((E4+E7)/2,0) -> 634 | F8: =ROUND((F4+F7)/2,0) -> 1082
A9: — on Single Plan | B9: =ROUND(B8*(1-Assumptions!B10),0) -> 27 | C9: =ROUND(C8*(1-Assumptions!C10),0) -> 105 | D9: =ROUND(D8*(1-Assumptions!D10),0) -> 251 | E9: =ROUND(E8*(1-Assumptions!E10),0) -> 476 | F9: =ROUND(F8*(1-Assumptions!F10),0) -> 757
A10: — on Multi Plan | B10: =ROUND(B8*Assumptions!B10,0) -> 3 | C10: =ROUND(C8*Assumptions!C10,0) -> 18 | D10: =ROUND(D8*Assumptions!D10,0) -> 63 | E10: =ROUND(E8*Assumptions!E10,0) -> 159 | F10: =ROUND(F8*Assumptions!F10,0) -> 325
A11: REVENUE (₹ Lakhs)
A12: Single Plan Revenue | B12: =ROUND(B9*Assumptions!B8*12/100000,2) -> 29.16 | C12: =ROUND(C9*Assumptions!C8*12/100000,2) -> 113.39 | D12: =ROUND(D9*Assumptions!D8*12/100000,2) -> 286.11 | E12: =ROUND(E9*Assumptions!E8*12/100000,2) -> 542.58 | F12: =ROUND(F9*Assumptions!F8*12/100000,2) -> 908.31
A13: Multi Plan Revenue | B13: =ROUND(B10*Assumptions!B9*12/100000,2) -> 5.4 | C13: =ROUND(C10*Assumptions!C9*12/100000,2) -> 32.4 | D13: =ROUND(D10*Assumptions!D9*12/100000,2) -> 120.95 | E13: =ROUND(E10*Assumptions!E9*12/100000,2) -> 305.26 | F13: =ROUND(F10*Assumptions!F9*12/100000,2) -> 662.96
A14: Total Revenue (₹ Lakhs) | B14: =B12+B13 -> 34.56 | C14: =C12+C13 -> 145.79 | D14: =D12+D13 -> 407.06 | E14: =E12+E13 -> 847.84 | F14: =F12+F13 -> 1571.27
A15: MoM Revenue Growth % | B15: - | C15: =IF(B14=0,0,(C14-B14)/B14) -> 3.2184606 | D15: =IF(C14=0,0,(D14-C14)/C14) -> 1.7920982 | E15: =IF(D14=0,0,(E14-D14)/D14) -> 1.0828379 | F15: =IF(E14=0,0,(F14-E14)/E14) -> 0.85326241
A16: ARR (₹ Lakhs) | B16: =ROUND(B7*(Assumptions!B8*(1-Assumptions!B10)+Assumptions!B9*Assumptions!B10)*12/100000,2) -> 69.11 | C16: =ROUND(C7*(Assumptions!C8*(1-Assumptions!C10)+Assumptions!C9*Assumptions!C10)*12/100000,2) -> 220.95 | D16: =ROUND(D7*(Assumptions!D8*(1-Assumptions!D10)+Assumptions!D9*Assumptions!D10)*12/100000,2) -> 571.48 | E16: =ROUND(E7*(Assumptions!E8*(1-Assumptions!E10)+Assumptions!E9*Assumptions!E10)*12/100000,2) -> 1102.61 | F16: =ROUND(F7*(Assumptions!F8*(1-Assumptions!F10)+Assumptions!F9*Assumptions!F10)*12/100000,2) -> 1941.16
A17: GROSS MARGIN
A18: Infrastructure & API Costs | B18: =-ROUND(B8*Assumptions!B18*12/100000,2) -> -1.8 | C18: =-ROUND(C8*Assumptions!C18*12/100000,2) -> -6.64 | D18: =-ROUND(D8*Assumptions!D18*12/100000,2) -> -15.07 | E18: =-ROUND(E8*Assumptions!E18*12/100000,2) -> -26.63 | F18: =-ROUND(F8*Assumptions!F18*12/100000,2) -> -38.95
A19: Gross Profit (₹ Lakhs) | B19: =B14+B18 -> 32.76 | C19: =C14+C18 -> 139.15 | D19: =D14+D18 -> 391.99 | E19: =E14+E18 -> 821.21 | F19: =F14+F18 -> 1532.32
A20: Gross Margin % | B20: =IF(B14=0,0,B19/B14) -> 0.94791667 | C20: =IF(C14=0,0,C19/C14) -> 0.95445504 | D20: =IF(D14=0,0,D19/D14) -> 0.96297843 | E20: =IF(E14=0,0,E19/E14) -> 0.96859077 | F20: =IF(F14=0,0,F19/F14) -> 0.97521113

Sheet P&L
A1: PROFIT & LOSS STATEMENT (₹ Lakhs)
B2: FY2025 | C2: FY2026 | D2: FY2027 | E2: FY2028 | F2: FY2029
A3: REVENUE
A4: Subscription Revenue | B4: ='Revenue Model'!B14 -> 34.56 | C4: ='Revenue Model'!C14 -> 145.79 | D4: ='Revenue Model'!D14 -> 407.06 | E4: ='Revenue Model'!E14 -> 847.84 | F4: ='Revenue Model'!F14 -> 1571.27
A5: Total Revenue | B5: =B4 -> 34.56 | C5: =C4 -> 145.79 | D5: =D4 -> 407.06 | E5: =E4 -> 847.84 | F5: =F4 -> 1571.27
A6: COST OF REVENUE
A7: Infrastructure & API Costs | B7: ='Revenue Model'!B18 -> -1.8 | C7: ='Revenue Model'!C18 -> -6.64 | D7: ='Revenue Model'!D18 -> -15.07 | E7: ='Revenue Model'!E18 -> -26.63 | F7: ='Revenue Model'!F18 -> -38.95
A8: Gross Profit | B8: =B5+B7 -> 32.76 | C8: =C5+C7 -> 139.15 | D8: =D5+D7 -> 391.99 | E8: =E5+E7 -> 821.21 | F8: =F5+F7 -> 1532.32
A9: Gross Margin % | B9: =IF(B5=0,0,B8/B5) -> 0.94791667 | C9: =IF(C5=0,0,C8/C5) -> 0.95445504 | D9: =IF(D5=0,0,D8/D5) -> 0.96297843 | E9: =IF(E5=0,0,E8/E5) -> 0.96859077 | F9: =IF(F5=0,0,F8/F5) -> 0.97521113
A10: OPERATING EXPENSES
A11: Founding Team Salaries | B11: =-Assumptions!B13*12 -> -36 | C11: =-Assumptions!C13*12 -> -60 | D11: =-Assumptions!D13*12 -> -96 | E11: =-Assumptions!E13*12 -> -144 | F11: =-Assumptions!F13*12 -> -192
A12: Engineering Team | B12: =-Assumptions!B14*Assumptions!B15*12 -> -36 | C12: =-Assumptions!C14*Assumptions!C15*12 -> -76.8 | D12: =-Assumptions!D14*Assumptions!D15*12 -> -142.8 | E12: =-Assumptions!E14*Assumptions!E15*12 -> -237.6 | F12: =-Assumptions!F14*Assumptions!F15*12 -> -342
A13: Sales & Marketing Team | B13: =-Assumptions!B16*Assumptions!B17*12 -> -19.2 | C13: =-Assumptions!C16*Assumptions!C17*12 -> -43.2 | D13: =-Assumptions!D16*Assumptions!D17*12 -> -96 | E13: =-Assumptions!E16*Assumptions!E17*12 -> -184.8 | F13: =-Assumptions!F16*Assumptions!F17*12 -> -288
A14: Sales & Marketing Spend | B14: =-B5*Assumptions!B20 -> -10.368 | C14: =-C5*Assumptions!C20 -> -36.4475 | D14: =-D5*Assumptions!D20 -> -89.5532 | E14: =-E5*Assumptions!E20 -> -169.568 | F14: =-F5*Assumptions!F20 -> -282.8286
A15: General & Administrative | B15: =-Assumptions!B19*12 -> -6 | C15: =-Assumptions!C19*12 -> -9.6 | D15: =-Assumptions!D19*12 -> -14.4 | E15: =-Assumptions!E19*12 -> -21.6 | F15: =-Assumptions!F19*12 -> -30
A16: Total OpEx | B16: =SUM(B11:B15) -> -107.568 | C16: =SUM(C11:C15) -> -226.0475 | D16: =SUM(D11:D15) -> -438.7532 | E16: =SUM(E11:E15) -> -757.568 | F16: =SUM(F11:F15) -> -1134.8286
A17: EBITDA | B17: =B8+B16 -> -74.808 | C17: =C8+C16 -> -86.8975 | D17: =D8+D16 -> -46.7632 | E17: =E8+E16 -> 63.642 | F17: =F8+F16 -> 397.4914
A18: EBITDA Margin % | B18: =IF(B5=0,0,B17/B5) -> -2.1645833 | C18: =IF(C5=0,0,C17/C5) -> -0.59604568 | D18: =IF(D5=0,0,D17/D5) -> -0.11488036 | E18: =IF(E5=0,0,E17/E5) -> 0.075063691 | F18: =IF(F5=0,0,F17/F5) -> 0.2529746
A19: Depreciation & Amortisation | B19: =-B5*0.05 -> -1.728 | C19: =-C5*0.05 -> -7.2895 | D19: =-D5*0.05 -> -20.353 | E19: =-E5*0.05 -> -42.392 | F19: =-F5*0.05 -> -78.5635
A20: EBIT | B20: =B17+B19 -> -76.536 | C20: =C17+C19 -> -94.187 | D20: =D17+D19 -> -67.1162 | E20: =E17+E19 -> 21.25 | F20: =F17+F19 -> 318.9279
A21: Tax (25%) | B21: =IF(B20>0,-B20*0.25,0) -> 0 | C21: =IF(C20>0,-C20*0.25,0) -> 0 | D21: =IF(D20>0,-D20*0.25,0) -> 0 | E21: =IF(E20>0,-E20*0.25,0) -> -5.3125 | F21: =IF(F20>0,-F20*0.25,0) -> -79.731975
A22: NET PROFIT / (LOSS) | B22: =B20+B21 -> -76.536 | C22: =C20+C21 -> -94.187 | D22: =D20+D21 -> -67.1162 | E22: =E20+E21 -> 15.9375 | F22: =F20+F21 -> 239.19592
A23: Net Margin % | B23: =IF(B5=0,0,B22/B5) -> -2.2145833 | C23: =IF(C5=0,0,C22/C5) -> -0.64604568 | D23: =IF(D5=0,0,D22/D5) -> -0.16488036 | E23: =IF(E5=0,0,E22/E5) -> 0.018797768 | F23: =IF(F5=0,0,F22/F5) -> 0.15223095

Sheet Cash Flow
A1: CASH FLOW STATEMENT (₹ Lakhs)
B2: FY2025 | C2: FY2026 | D2: FY2027 | E2: FY2028 | F2: FY2029
A3: OPERATING ACTIVITIES
A4: Net Profit / (Loss) | B4: ='P&L'!B22 -> -76.536 | C4: ='P&L'!C22 -> -94.187 | D4: ='P&L'!D22 -> -67.1162 | E4: ='P&L'!E22 -> 15.9375 | F4: ='P&L'!F22 -> 239.19592
A5: Add: Depreciation & Amort. | B5: =-'P&L'!B19 -> 1.728 | C5: =-'P&L'!C19 -> 7.2895 | D5: =-'P&L'!D19 -> 20.353 | E5: =-'P&L'!E19 -> 42.392 | F5: =-'P&L'!F19 -> 78.5635
A6: Working Capital Changes | B6: =-'Revenue Model'!B14*0.05 -> -1.728 | C6: =-'Revenue Model'!C14*0.05 -> -7.2895 | D6: =-'Revenue Model'!D14*0.05 -> -20.353 | E6: =-'Revenue Model'!E14*0.05 -> -42.392 | F6: =-'Revenue Model'!F14*0.05 -> -78.5635
A7: Cash from Operations | B7: =B4+B5+B6 -> -76.536 | C7: =C4+C5+C6 -> -94.187 | D7: =D4+D5+D6 -> -67.1162 | E7: =E4+E5+E6 -> 15.9375 | F7: =F4+F5+F6 -> 239.19592
A8: INVESTING ACTIVITIES
A9: Tech / Product Investment | B9: =-'Revenue Model'!B14*0.1 -> -3.456 | C9: =-'Revenue Model'!C14*0.1 -> -14.579 | D9: =-'Revenue Model'!D14*0.1 -> -40.706 | E9: =-'Revenue Model'!E14*0.1 -> -84.784 | F9: =-'Revenue Model'!F14*0.1 -> -157.127
A10: Cash from Investing | B10: =B9 -> -3.456 | C10: =C9 -> -14.579 | D10: =D9 -> -40.706 | E10: =E9 -> -84.784 | F10: =F9 -> -157.127
A11: FINANCING ACTIVITIES
A12: Equity Raised | B12: 50 | C12: 0 | D12: 150 | E12: 0 | F12: 0
A13: Cash from Financing | B13: =B12 -> 50 | C13: =C12 -> 0 | D13: =D12 -> 150 | E13: =E12 -> 0 | F13: =F12 -> 0
A14: NET CASH FLOW | B14: =B7+B10+B13 -> -29.992 | C14: =C7+C10+C13 -> -108.766 | D14: =D7+D10+D13 -> 42.1778 | E14: =E7+E10+E13 -> -68.8465 | F14: =F7+F10+F13 -> 82.068925
A15: Opening Cash Balance | B15: 0 | C15: =B16 -> -29.992 | D15: =C16 -> -138.758 | E15: =D16 -> -96.5802 | F15: =E16 -> -165.4267
A16: Closing Cash Balance | B16: =B15+B14 -> -29.992 | C16: =C15+C14 -> -138.758 | D16: =D15+D14 -> -96.5802 | E16: =E15+E14 -> -165.4267 | F16: =F15+F14 -> -83.357775

Sheet Unit Economics
A1: UNIT ECONOMICS — CAC, LTV, Payback & Cohort Metrics
B2: FY2025 | C2: FY2026 | D2: FY2027 | E2: FY2028 | F2: FY2029
A3: ACQUISITION
A4: New Dealers (Annual) | B4: ='Revenue Model'!B5 -> 60 | C4: ='Revenue Model'!C5 -> 144 | D4: ='Revenue Model'!D5 -> 300 | E4: ='Revenue Model'!E5 -> 480 | F4: ='Revenue Model'!F5 -> 660
A5: S&M Team Cost (₹L) | B5: =-'P&L'!B13 -> 19.2 | C5: =-'P&L'!C13 -> 43.2 | D5: =-'P&L'!D13 -> 96 | E5: =-'P&L'!E13 -> 184.8 | F5: =-'P&L'!F13 -> 288
A6: S&M Spend (₹L) | B6: =-'P&L'!B14 -> 10.368 | C6: =-'P&L'!C14 -> 36.4475 | D6: =-'P&L'!D14 -> 89.5532 | E6: =-'P&L'!E14 -> 169.568 | F6: =-'P&L'!F14 -> 282.8286
A7: Total Acquisition Cost (₹L) | B7: =B5+B6 -> 29.568 | C7: =C5+C6 -> 79.6475 | D7: =D5+D6 -> 185.5532 | E7: =E5+E6 -> 354.368 | F7: =F5+F6 -> 570.8286
A8: CAC (₹ per dealer) | B8: =IF(B4=0,0,B7*100000/B4) -> 49280 | C8: =IF(C4=0,0,C7*100000/C4) -> 55310.764 | D8: =IF(D4=0,0,D7*100000/D4) -> 61851.067 | E8: =IF(E4=0,0,E7*100000/E4) -> 73826.667 | F8: =IF(F4=0,0,F7*100000/F4) -> 86489.182
A9: MONETISATION
A10: ARPU (₹/month) | B10: =Assumptions!B23 -> 9599 | C10: =Assumptions!C23 -> 9899 | D10: =Assumptions!D23 -> 10799 | E10: =Assumptions!E23 -> 11124 | F10: =Assumptions!F23 -> 12099
A11: Monthly Churn Rate | B11: =Assumptions!B6 -> 0.03 | C11: =Assumptions!C6 -> 0.025 | D11: =Assumptions!D6 -> 0.02 | E11: =Assumptions!E6 -> 0.018 | F11: =Assumptions!F6 -> 0.015
A12: Avg Customer Lifetime (months) | B12: =IF(Assumptions!B6=0,0,1/Assumptions!B6) -> 33.333333 | C12: =IF(Assumptions!C6=0,0,1/Assumptions!C6) -> 40 | D12: =IF(Assumptions!D6=0,0,1/Assumptions!D6) -> 50 | E12: =IF(Assumptions!E6=0,0,1/Assumptions!E6) -> 55.555556 | F12: =IF(Assumptions!F6=0,0,1/Assumptions!F6) -> 66.666667
A13: LTV (₹) | B13: =IF(Assumptions!B6=0,0,B10/Assumptions!B6) -> 319966.67 | C13: =IF(Assumptions!C6=0,0,C10/Assumptions!C6) -> 395960 | D13: =IF(Assumptions!D6=0,0,D10/Assumptions!D6) -> 539950 | E13: =IF(Assumptions!E6=0,0,E10/Assumptions!E6) -> 618000 | F13: =IF(Assumptions!F6=0,0,F10/Assumptions!F6) -> 806600
A14: LTV / CAC Ratio | B14: =IF(B8=0,0,B13/B8*100000) -> 649283.01 | C14: =IF(C8=0,0,C13/C8*100000) -> 715882.36 | D14: =IF(D8=0,0,D13/D8*100000) -> 872984.14 | E14: =IF(E8=0,0,E13/E8*100000) -> 837095.9 | F14: =IF(F8=0,0,F13/F8*100000) -> 932602.19
A15: Payback Period (months) | B15: =IF(B10=0,0,B8/100000/B10) -> 5.1338681e-05 | C15: =IF(C10=0,0,C8/100000/C10) -> 5.5875102e-05 | D15: =IF(D10=0,0,D8/100000/D10) -> 5.7274809e-05 | E15: =IF(E10=0,0,E8/100000/E10) -> 6.6367014e-05 | F15: =IF(F10=0,0,F8/100000/F10) -> 7.148457e-05
A16: COHORT & HEALTH
A17: MRR End of Year (₹L) | B17: ='Revenue Model'!B7*B10/100000 -> 5.7594 | C17: ='Revenue Model'!C7*C10/100000 -> 18.41214 | D17: ='Revenue Model'!D7*D10/100000 -> 47.62359 | E17: ='Revenue Model'!E7*E10/100000 -> 91.88424 | F17: ='Revenue Model'!F7*F10/100000 -> 161.76363
A18: ARR End of Year (₹L) | B18: =B17*12 -> 69.1128 | C18: =C17*12 -> 220.94568 | D18: =D17*12 -> 571.48308 | E18: =E17*12 -> 1102.6109 | F18: =F17*12 -> 1941.1636
A19: MRR Growth YoY | B19: - | C19: =IF(B17=0,0,(C17-B17)/B17) -> 2.1968851 | D19: =IF(C17=0,0,(D17-C17)/C17) -> 1.586532 | E19: =IF(D17=0,0,(E17-D17)/D17) -> 0.929385 | F19: =IF(E17=0,0,(F17-E17)/E17) -> 0.76051551
A20: Net Revenue Retention | B20: =1-Assumptions!B6+0.05 -> 1.02 | C20: =1-Assumptions!C6+0.05 -> 1.025 | D20: =1-Assumptions!D6+0.05 -> 1.03 | E20: =1-Assumptions!E6+0.05 -> 1.032 | F20: =1-Assumptions!F6+0.05 -> 1.035

Sheet Scenarios
A1: SCENARIO ANALYSIS — Bear / Base / Bull Case (FY2029)
A2: Metric | B2: Bear Case | C2: Base Case | D2: Bull Case
A3: ASSUMPTIONS
A4: New Dealers/month (FY2029) | B4: 30 | C4: 55 | D4: 90
A5: Monthly Churn Rate | B5: 0.03 | C5: 0.015 | D5: 0.008
A6: ARPU (₹/month) | B6: 8999 | C6: 11500 | D6: 13500
A7: Gross Margin % | B7: 0.6 | C7: 0.75 | D7: 0.82
A8: S&M as % Revenue | B8: 0.28 | C8: 0.18 | D8: 0.12
A9: OUTCOMES (FY2029)
A10: Total Dealers (End FY29) | B10: 280 | C10: 780 | D10: 1600
A11: ARR (₹ Lakhs) | B11: 251 | C11: 1071 | D11: 2160
A12: Gross Profit (₹ Lakhs) | B12: 151 | C12: 803 | D12: 1771
A13: EBITDA (₹ Lakhs) | B13: -40 | C13: 310 | D13: 950
A14: EBITDA Margin % | B14: -0.16 | C14: 0.29 | D14: 0.44
A15: LTV/CAC | B15: 1.2 | C15: 4.8 | D15: 9.5
